open_insider/__init__.py
open_insider/date_functions.py
open_insider-0.1.0.dist-info/METADATA
open_insider-0.1.0.dist-info/WHEEL
open_insider-0.1.0.dist-info/top_level.txt
open_insider-0.1.0.dist-info/RECORD
