Metadata-Version: 2.1
Name: open-insider
Version: 0.1.0
Summary: Demo library
Home-page: https://open-insider.readthedocs.io/
Author: Nils Skoglund
Author-email: example@email.com
License: UNKNOWN
Platform: UNKNOWN
Classifier: Intended Audience :: Developers
Classifier: Programming Language :: Python
Classifier: Programming Language :: Python :: 3
Classifier: Programming Language :: Python :: 3.8
Classifier: Programming Language :: Python :: 3.9
Classifier: Operating System :: OS Independent
Requires-Dist: pandas
